markback/__init__.py
markback/cli.py
markback/config.py
markback/linter.py
markback/llm.py
markback/parser.py
markback/types.py
markback/workflow.py
markback/writer.py
markback-0.1.3.dist-info/METADATA
markback-0.1.3.dist-info/WHEEL
markback-0.1.3.dist-info/entry_points.txt
markback-0.1.3.dist-info/licenses/LICENSE
markback-0.1.3.dist-info/RECORD
