Metadata-Version: 2.4
Name: markback
Version: 0.1.3
Summary: A compact, human-writable format for storing content paired with feedback/labels
Project-URL: Homepage, https://github.com/dandriscoll/markback
Project-URL: Repository, https://github.com/dandriscoll/markback
Project-URL: Documentation, https://github.com/dandriscoll/markback#readme
Project-URL: Issues, https://github.com/dandriscoll/markback/issues
Author: Dan Driscoll
License-Expression: MIT
License-File: LICENSE
Keywords: annotation,data-labeling,feedback,labeling,llm,markdown
Classifier: Development Status :: 3 - Alpha
Classifier: Environment :: Console
Classifier: Intended Audience :: Developers
Classifier: License :: OSI Approved :: MIT License
Classifier: Operating System :: OS Independent
Classifier: Programming Language :: Python :: 3
Classifier: Programming Language :: Python :: 3.10
Classifier: Programming Language :: Python :: 3.11
Classifier: Programming Language :: Python :: 3.12
Classifier: Topic :: Software Development :: Quality Assurance
Classifier: Topic :: Text Processing :: Markup
Requires-Python: >=3.10
Requires-Dist: httpx>=0.25.0
Requires-Dist: python-dotenv>=1.0.0
Requires-Dist: rich>=13.0.0
Requires-Dist: typer>=0.9.0
Provides-Extra: dev
Requires-Dist: build>=1.0.0; extra == 'dev'
Requires-Dist: pytest-cov>=4.0.0; extra == 'dev'
Requires-Dist: pytest>=7.0.0; extra == 'dev'
Requires-Dist: twine>=5.0.0; extra == 'dev'
